indico_previewer_code/__init__.py
indico_previewer_code/plugin.py
indico_previewer_code/templates/pygments_preview.html
indico_plugin_previewer_code-3.3.dist-info/METADATA
indico_plugin_previewer_code-3.3.dist-info/WHEEL
indico_plugin_previewer_code-3.3.dist-info/entry_points.txt
indico_plugin_previewer_code-3.3.dist-info/top_level.txt
indico_plugin_previewer_code-3.3.dist-info/RECORD
