Metadata-Version: 2.1
Name: indico-plugin-previewer-code
Version: 3.3
Summary: Syntax highlighter for code attachments in Indico
Home-page: https://github.com/indico/indico-plugins
Author: Indico Team
Author-email: indico-team@cern.ch
License: MIT
Classifier: Environment :: Plugins
Classifier: Environment :: Web Environment
Classifier: License :: OSI Approved :: MIT License
Classifier: Programming Language :: Python :: 3.12
Requires-Python: <3.13,>=3.12.2
Requires-Dist: indico >=3.3
Requires-Dist: Pygments <3,>=2.7.2
